ukw_tools/__init__.py
ukw_tools/classes/__init__.py
ukw_tools/classes/annotation.py
ukw_tools/classes/base.py
ukw_tools/classes/data_gen.py
ukw_tools/classes/db.py
ukw_tools/classes/db_validator.py
ukw_tools/classes/examination.py
ukw_tools/classes/image.py
ukw_tools/classes/model_handler.py
ukw_tools/classes/prediction.py
ukw_tools/classes/report.py
ukw_tools/classes/trainer_handler.py
ukw_tools/classes/utils.py
ukw_tools/classes/video_segmentation.py
ukw_tools/extern/__init__.py
ukw_tools/extern/classes.py
ukw_tools/extern/requests.py
ukw_tools/extern/smartie.py
ukw_tools/extern/video_annotations.py
ukw_tools/metrics/__init__.py
ukw_tools/metrics/base.py
ukw_tools/model/__init__.py
ukw_tools/model/multilabel_classification_net.py
ukw_tools/model/utils.py
ukw_tools/model/wandb_callbacks.py
ukw_tools-0.0.2.dist-info/LICENSE
ukw_tools-0.0.2.dist-info/METADATA
ukw_tools-0.0.2.dist-info/WHEEL
ukw_tools-0.0.2.dist-info/top_level.txt
ukw_tools-0.0.2.dist-info/RECORD
