Metadata-Version: 2.1
Name: ukw-tools
Version: 0.0.2
Summary: Package all around AI in colonoscopy.
Home-page: https://github.com/Maddonix/ukw_tools
Author: Thomas J. Lux
Author-email: tlux14@gmail.com
License: UNKNOWN
Project-URL: Bug Tracker, https://github.com/pypa/sampleproject/issues
Platform: UNKNOWN
Classifier: Programming Language :: Python :: 3
Classifier: Operating System :: OS Independent
Requires-Python: >=3.9
License-File: LICENSE
